fennlp/__init__.py
fennlp/savers.py
fennlp/tools.py
fennlp/abandoned/GCNConvv0.py
fennlp/abandoned/__init__.py
fennlp/abandoned/scatter.py
fennlp/datas/__init__.py
fennlp/datas/checkpoint.py
fennlp/datas/dataloader.py
fennlp/datas/graphloader.py
fennlp/datas/word2vec.py
fennlp/gnn/GCNConv.py
fennlp/gnn/RGCNConv.py
fennlp/gnn/__init__.py
fennlp/gnn/messagepassing.py
fennlp/gnn/scatter.py
fennlp/gnn/utils.py
fennlp/layers/__init__.py
fennlp/layers/albert_transformer.py
fennlp/layers/attention.py
fennlp/layers/bilstm.py
fennlp/layers/decoder.py
fennlp/layers/dense.py
fennlp/layers/embedding.py
fennlp/layers/gpt2_transformer.py
fennlp/layers/normalization.py
fennlp/layers/transformer.py
fennlp/metrics/Losess.py
fennlp/metrics/Metric.py
fennlp/metrics/__init__.py
fennlp/metrics/crf.py
fennlp/metrics/n_crf.py
fennlp/metrics/type.py
fennlp/models/GCN.py
fennlp/models/PCNN.py
fennlp/models/RGCN.py
fennlp/models/TextCNN.py
fennlp/models/__init__.py
fennlp/models/albert.py
fennlp/models/bert.py
fennlp/models/gpt2.py
fennlp/models/tucker.py
fennlp/optimizers/__init__.py
fennlp/optimizers/optim.py
fennlp/tokenizers/__init__.py
fennlp/tokenizers/albert_tokenization.py
fennlp/tokenizers/gpt2_tokenization.py
fennlp/tokenizers/tokenization.py
fennlp-0.0.7.dist-info/LICENSE
fennlp-0.0.7.dist-info/METADATA
fennlp-0.0.7.dist-info/WHEEL
fennlp-0.0.7.dist-info/top_level.txt
fennlp-0.0.7.dist-info/RECORD
