Metadata-Version: 2.1
Name: fennlp
Version: 0.0.7
Summary: An out-of-the-box NLP toolkit can easily help you solve tasks such as              Entity Recognition, Text Classification, Relation Extraction and so on.
Home-page: https://github.com/kyzhouhzau/fennlp
Author: Kaiyin Zhou
Author-email: zhoukaiyinhzau@gmail.com
License: Apache
Platform: UNKNOWN
Classifier: Programming Language :: Python
Requires-Python: >=3.6.0
Requires-Dist: typeguard
Requires-Dist: gensim
Requires-Dist: tqdm
Requires-Dist: regex
Requires-Dist: scikit-learn
Requires-Dist: sentencepiece
